README.md
pyproject.toml
setup.cfg
setup.py
baseapp_url_shortening/__init__.py
baseapp_url_shortening/admin.py
baseapp_url_shortening/apps.py
baseapp_url_shortening/models.py
baseapp_url_shortening/urls.py
baseapp_url_shortening/utils.py
baseapp_url_shortening/views.py
baseapp_url_shortening.egg-info/PKG-INFO
baseapp_url_shortening.egg-info/SOURCES.txt
baseapp_url_shortening.egg-info/dependency_links.txt
baseapp_url_shortening.egg-info/requires.txt
baseapp_url_shortening.egg-info/top_level.txt
baseapp_url_shortening/migrations/0001_initial.py
baseapp_url_shortening/migrations/0002_alter_shorturl_full_url.py
baseapp_url_shortening/migrations/__init__.py
baseapp_url_shortening/tests/__init__.py
baseapp_url_shortening/tests/conftest.py
baseapp_url_shortening/tests/factories.py
baseapp_url_shortening/tests/settings.py
baseapp_url_shortening/tests/integration/__init__.py
baseapp_url_shortening/tests/integration/test_url_shortening.py
testproject/__init__.py
testproject/settings.py
testproject/urls.py