Metadata-Version: 2.1
Name: baseapp-url-shortening
Version: 0.1.31
Summary: BaseApp URL Shortening
Home-page: https://github.com/silverlogic/baseapp-backend
Author: The SilverLogic
Author-email: dev@tsl.io
License: BSD-3-Clause  # Example license
Platform: UNKNOWN
Requires-Python: >=3.8
